Horsesale.py
Horsesale-0.0.1.dist-info/METADATA
Horsesale-0.0.1.dist-info/WHEEL
Horsesale-0.0.1.dist-info/entry_points.txt
Horsesale-0.0.1.dist-info/top_level.txt
Horsesale-0.0.1.dist-info/RECORD
