Metadata-Version: 2.1
Name: Horsesale
Version: 0.0.1
Summary: A package designed to help you understand the trends of nations that host high-level G1 races.
Home-page: https://github.com/Kiuchi424/Horsesale
Author: Kiuchi_424
Author-email: s1922059@stu.musashino-u.ac.jp
License: UNKNOWN
Project-URL: Horsesale, https://github.com/Kiuchi424/Horsesale
Platform: UNKNOWN
Classifier: Programming Language :: Python :: 3
Classifier: License :: OSI Approved :: MIT License
Classifier: Operating System :: OS Independent
Requires-Python: >=3.6
